seqtk/__init__.py
seqtk/_concatenate.py
seqtk/_gather.py
seqtk/_helper.py
seqtk/_map.py
seqtk/py.typed
seqtk-0.4.0.dist-info/LICENSE
seqtk-0.4.0.dist-info/METADATA
seqtk-0.4.0.dist-info/WHEEL
seqtk-0.4.0.dist-info/top_level.txt
seqtk-0.4.0.dist-info/RECORD
