Metadata-Version: 2.1
Name: seqtk
Version: 0.4.0
Summary: seqtk provides various tools for Sequence.
Home-page: https://github.com/yuyu2172/seqtk
Author: Yusuke Niitani
Author-email: UNKNOWN
License: UNKNOWN
Platform: UNKNOWN
